README.rst
setup.cfg
setup.py
remarkable_fs/__init__.py
remarkable_fs/connection.py
remarkable_fs/documents.py
remarkable_fs/fs.py
remarkable_fs/rM2svg.py
remarkable_fs.egg-info/PKG-INFO
remarkable_fs.egg-info/SOURCES.txt
remarkable_fs.egg-info/dependency_links.txt
remarkable_fs.egg-info/entry_points.txt
remarkable_fs.egg-info/requires.txt
remarkable_fs.egg-info/top_level.txt