Metadata-Version: 1.1
Name: remarkable-fs
Version: 0.1.2
Summary: A FUSE filesystem driver for the reMarkable tablet
Home-page: https://github.com/nick8325/remarkable-fs
Author: Nick Smallbone
Author-email: nick@smallbone.se
License: UNKNOWN
Keywords: remarkable fuse
Platform: UNKNOWN
Classifier: Development Status :: 2 - Pre-Alpha
Classifier: Intended Audience :: End Users/Desktop
Classifier: License :: OSI Approved :: MIT License
Classifier: Programming Language :: Python :: 2.7
Classifier: Programming Language :: Python :: 3.5
Classifier: Operating System :: MacOS :: MacOS X
Classifier: Operating System :: POSIX
Classifier: Operating System :: POSIX :: Linux
Classifier: Topic :: System :: Hardware
Classifier: Topic :: System :: Filesystems
Classifier: Topic :: Utilities
